{"name":"Play-new-passcheckstyle","tagline":"A default play project that passes checkstyle.","body":"The default Java play application generated by running the \"play new\" command contains a number of\r\nstylistic problems, including:\r\n\r\n  * Wildcard imports.\r\n  * Superfluous imports (referencing code not used in class).\r\n  * No package-level documentation (i.e. no package-info.java files).\r\n  * No class or method level JavaDocs.\r\n  * Inconsistent indentation.\r\n  \r\nWhen such an application is processed using Checkstyle with a reasonable ruleset, \r\napproximately 50 warnings are generated.\r\n\r\nThis application provides a corrected version of the default Java Play application, with all of\r\nthose warnings removed.  \r\n   \r\n","google":"","note":"Don't delete this file! It's used internally to help with page regeneration."}